pypepp-0.0.2.dist-info/RECORD
pypepp-0.0.2.dist-info/WHEEL
pypepp-0.0.2.dist-info/METADATA
pypepp-0.0.2.dist-info/licenses/LICENSE
pypepp/pypepp_native.cpython-312-darwin.so
pypepp/CMakeLists.txt
pypepp/__init__.py
pypepp/README.md
pypepp/dummy.cpp
pypepp/.gitignore
pypepp/main.py
