Metadata-Version: 2.4
Name: pypepp
Version: 0.0.2
Summary: Python bindings for the Pepp assembler and simulator
Author-Email: Matthew McRaven <matthew.mcraven@gmail.com>
License-Expression: GPL-3.0-or-later
License-File: LICENSE
Project-URL: Homepage, https://github.com/Matthew-McRaven/Pepp
Project-URL: Issues, https://github.com/Matthew-McRaven/Pepp/issues
Requires-Python: >=3.12
